MANIFEST.in
README.rst
setup.py
yopy.py
yopy.egg-info/PKG-INFO
yopy.egg-info/SOURCES.txt
yopy.egg-info/dependency_links.txt
yopy.egg-info/entry_points.txt
yopy.egg-info/not-zip-safe
yopy.egg-info/requires.txt
yopy.egg-info/top_level.txt