Metadata-Version: 1.1
Name: yopy
Version: 1.0
Summary: Zero characters communication for humans.
Home-page: https://github.com/sloria/yopy
Author: Steven Loria
Author-email: sloria1@gmail.com
License: UNKNOWN
Platform: UNKNOWN
Classifier: Development Status :: 5 - Production/Stable
Classifier: License :: OSI Approved :: MIT License
Classifier: Natural Language :: English
Classifier: Programming Language :: Python :: 2
Classifier: Programming Language :: Python :: 2.7
Classifier: Programming Language :: Python :: 3
Classifier: Programming Language :: Python :: 3.4
Classifier: Programming Language :: Python :: Implementation :: CPython
